pjsekai_background_gen_pillow/__init__.py
pjsekai_background_gen_pillow/__main__.py
pjsekai_background_gen_pillow/assets/background-base.png
pjsekai_background_gen_pillow/assets/dot-tilea.png
pjsekai_background_gen_pillow/assets/frame.png
pjsekai_background_gen_pillow/assets/mask.png
pjsekai_background_gen_pillow/assets/side-mask.png
pjsekai_background_gen_pillow/core.py
pjsekai_background_gen_pillow-0.3.0.dist-info/entry_points.txt
pjsekai_background_gen_pillow-0.3.0.dist-info/LICENSE
pjsekai_background_gen_pillow-0.3.0.dist-info/WHEEL
pjsekai_background_gen_pillow-0.3.0.dist-info/METADATA
pjsekai_background_gen_pillow-0.3.0.dist-info/RECORD
